LICENSE
MANIFEST.in
README.rst
kthresher.8
kthresher.conf
kthresher.py
setup.py
kthresher.egg-info/PKG-INFO
kthresher.egg-info/SOURCES.txt
kthresher.egg-info/dependency_links.txt
kthresher.egg-info/entry_points.txt
kthresher.egg-info/top_level.txt