Metadata-Version: 1.1
Name: kthresher
Version: 1.3.0
Summary: Purge Unused Kernels.
Home-page: https://github.com/rackerlabs/kthresher
Author: Tony Garcia
Author-email: tony.garcia@rackspace.com
License: Apache License, Version 2.0
Download-URL: https://github.com/rackerlabs/kthresher/tarball/1.3.0
Platform: UNKNOWN
Classifier: Development Status :: 5 - Production/Stable
Classifier: Programming Language :: Python
Classifier: Environment :: Console
Classifier: Operating System :: POSIX :: Linux
Classifier: License :: OSI Approved :: Apache Software License
Classifier: Programming Language :: Python :: 2.7
